qtt/__init__.py
qtt/finetune/image/classification/__init__.py
qtt/finetune/image/classification/fn.py
qtt/finetune/image/classification/utils.py
qtt/optimizers/__init__.py
qtt/optimizers/optimizer.py
qtt/optimizers/quick.py
qtt/optimizers/rndm.py
qtt/predictors/__init__.py
qtt/predictors/cost.py
qtt/predictors/data.py
qtt/predictors/models.py
qtt/predictors/perf.py
qtt/predictors/predictor.py
qtt/predictors/utils.py
qtt/tuners/__init__.py
qtt/tuners/quick.py
qtt/tuners/image/__init__.py
qtt/tuners/image/classification/__init__.py
qtt/tuners/image/classification/tuner.py
qtt/utils/__init__.py
qtt/utils/config.py
qtt/utils/log_utils.py
qtt/utils/pretrained.py
qtt/utils/setup.py
quicktunetool-0.0.3.dist-info/LICENSE
quicktunetool-0.0.3.dist-info/METADATA
quicktunetool-0.0.3.dist-info/WHEEL
quicktunetool-0.0.3.dist-info/top_level.txt
quicktunetool-0.0.3.dist-info/RECORD
