Metadata-Version: 2.2
Name: quicktunetool
Version: 0.0.3
Summary: A Framework for Efficient Model Selection and Hyperparameter Optimization
Author-email: Ivo Rapant <rapanti@cs.uni-freiburg.de>
License: BSD 3-Clause License
Project-URL: Homepage, https://github.com/automl/quicktunetool
Project-URL: Bug Reports, https://github.com/automl/quicktunetool/issues
Project-URL: Source, https://github.com/automl/quicktunetool
Keywords: Machine Learning,AutoML,HPO,Fine-Tuning,Meta-Learning
Classifier: Development Status :: 3 - Alpha
Classifier: Intended Audience :: Developers
Classifier: Intended Audience :: Science/Research
Classifier: License :: OSI Approved :: BSD License
Classifier: Operating System :: Unix
Classifier: Programming Language :: Python
Classifier: Programming Language :: Python :: 3.11
Classifier: Topic :: Software Development :: Build Tools
Requires-Python: >=3.11
License-File: LICENSE
Requires-Dist: torch>2.0.0
Requires-Dist: torchvision>=0.15.1
Requires-Dist: ConfigSpace>=1.2.0
Requires-Dist: gpytorch>=1.9.0
Requires-Dist: numpy<2
Requires-Dist: pandas>=2.0.0
Requires-Dist: pyyaml>=6.0.1
Requires-Dist: scikit-learn==1.5.0
Requires-Dist: tqdm>=4.66.0
Requires-Dist: fimm
